imc_prospector-0.1.1.dist-info/licenses/LICENSE
imcprospector/__init__.py
imcprospector/__main__.py
imcprospector/checker.py
imcprospector/prosperity_config.yaml
imcprospector/py.typed
imcprospector/submit.py
imc_prospector-0.1.1.dist-info/METADATA
imc_prospector-0.1.1.dist-info/WHEEL
imc_prospector-0.1.1.dist-info/entry_points.txt
imc_prospector-0.1.1.dist-info/top_level.txt
imc_prospector-0.1.1.dist-info/RECORD
