Metadata-Version: 2.4
Name: imc-prospector
Version: 0.1.1
Summary: CLI submitter and algorithm validator for IMC Prosperity competition
Author: arJ-V
License: MIT License
Project-URL: Repository, https://github.com/arJ-V/imc-prospector
Project-URL: Issues, https://github.com/arJ-V/imc-prospector/issues
Keywords: imc,prosperity,submit,submitter,checker,validator,trading,algorithm
Classifier: Development Status :: 4 - Beta
Classifier: Intended Audience :: Developers
Classifier: Intended Audience :: Financial and Insurance Industry
Classifier: License :: OSI Approved :: MIT License
Classifier: Programming Language :: Python :: 3
Classifier: Programming Language :: Python :: 3.9
Classifier: Programming Language :: Python :: 3.10
Classifier: Programming Language :: Python :: 3.11
Classifier: Programming Language :: Python :: 3.12
Requires-Python: >=3.9
License-File: LICENSE
Requires-Dist: keyring>=25.6.0
Requires-Dist: requests>=2.32.3
Requires-Dist: requests-toolbelt>=1.0.0
Requires-Dist: typer>=0.15.2
Requires-Dist: pyyaml>=6.0
Provides-Extra: dev
Requires-Dist: mypy>=1.15.0; extra == "dev"
Requires-Dist: ruff>=0.9.7; extra == "dev"
Requires-Dist: types-requests>=2.32.0; extra == "dev"
Requires-Dist: pytest>=8.0.0; extra == "dev"
Dynamic: license-file
